NmapQueryTool/__init__.py
NmapQueryTool/nmap_query.py
NmapQueryTool/run_tests.py
NmapQueryTool/lib/__init__.py
NmapQueryTool/lib/host_data.py
NmapQueryTool/lib/interaction_context.py
NmapQueryTool/lib/nmap_data.py
NmapQueryTool/lib/port_data.py
NmapQueryTool/lib/scan_data.py
NmapQueryTool/tst/__init__.py
NmapQueryTool/tst/integration_tests.py
nmap_query_tool-1.1.8.dist-info/LICENSE
nmap_query_tool-1.1.8.dist-info/METADATA
nmap_query_tool-1.1.8.dist-info/WHEEL
nmap_query_tool-1.1.8.dist-info/top_level.txt
nmap_query_tool-1.1.8.dist-info/RECORD
