Metadata-Version: 2.1
Name: nmap-query-tool
Version: 1.1.8
Summary: A tool for parsing and dynamically querying nmap scan data
Home-page: https://github.com/unheardof/NmapQueryTool
Author: Timothy Heard
License: UNKNOWN
Platform: UNKNOWN
Classifier: Programming Language :: Python :: 3
Classifier: License :: OSI Approved :: Apache Software License
Classifier: Operating System :: OS Independent
Classifier: Environment :: Console
License-File: LICENSE
